fnsecure/conditions/__init__.py
fnsecure/conditions/conditions.py
fnsecure/errors/__init__.py
fnsecure/errors/errors.py
fnsecure/exceptions/__init__.py
fnsecure/exceptions/exceptions.py
fnsecure/exceptions/functions.py
fnsecure/exceptions/types.py
fnsecure/fnsecure.py
fnsecure/shared/__init__.py
fnsecure/shared/common.py
fnsecure-0.2.1.dist-info/LICENSE
fnsecure-0.2.1.dist-info/METADATA
fnsecure-0.2.1.dist-info/WHEEL
fnsecure-0.2.1.dist-info/RECORD
