Metadata-Version: 2.1
Name: fnsecure
Version: 0.2.1
Summary: Make python functions more secure and descriptive.
License: GNU GENERAL PUBLIC LICENSE  Version 2
Author: richard-rikk
Author-email: rikk.richard@gmail.com
Requires-Python: >=3.10,<4.0
Classifier: License :: Other/Proprietary License
Classifier: Programming Language :: Python :: 3
Classifier: Programming Language :: Python :: 3.10
Classifier: Programming Language :: Python :: 3.11
Classifier: Programming Language :: Python :: 3.12
